conta_bancaria/__init__.py
conta_bancaria/sistema_bancario.py
conta_bancaria-0.0.1.dist-info/METADATA
conta_bancaria-0.0.1.dist-info/WHEEL
conta_bancaria-0.0.1.dist-info/top_level.txt
conta_bancaria-0.0.1.dist-info/RECORD
