Metadata-Version: 2.1
Name: conta_bancaria
Version: 0.0.1
Summary: Exemplo de empacotamento
Home-page: https://github.com/felipedick/dio-classes/tree/main/5.%20POO/Pacote%20Conta%20Bancaria
Author: Felipe Dick
Author-email: example@gmail.com
Requires-Python: >=3.10
